upt/__init__.py
upt/__main__.py
upt/baseparser.py
upt/configmanager.py
upt/constants.py
upt/driver.py
upt/initparser.py
upt/sampler.py
upt/serviceparser.py
upt/session.py
upt-builtin/__init__.py
upt-builtin/atcoder.py
upt-builtin/codeforces.py
upt-builtin/quera.py
upt-builtin/usaco.py
universal_parser_tool-5.0.1.dist-info/LICENSE
universal_parser_tool-5.0.1.dist-info/METADATA
universal_parser_tool-5.0.1.dist-info/WHEEL
universal_parser_tool-5.0.1.dist-info/entry_points.txt
universal_parser_tool-5.0.1.dist-info/top_level.txt
universal_parser_tool-5.0.1.dist-info/RECORD
