Metadata-Version: 2.1
Name: universal-parser-tool
Version: 5.0.1
Summary: Useful tool to speedup testing in cp-programming
Home-page: https://github.com/ParsaAlizadeh/universal-parser-tool
Author: Parsa Alizadeh
Author-email: parsa.alizadeh1@gmail.com
License: GPL-3.0
Requires-Python: >=3.6
License-File: LICENSE
Requires-Dist: selenium (<5,>=3.141)
Requires-Dist: requests (<3,>=2.25)
Requires-Dist: beautifulsoup4 (<5,>=4.9)
Requires-Dist: markdown (<4,>=3.3)
